json2capella/__init__.py
json2capella/__main__.py
json2capella/datatypes.py
json2capella/importer.py
json2capella-0.3.1.dist-info/licenses/LICENSES/Apache-2.0.txt
json2capella-0.3.1.dist-info/licenses/LICENSES/CC0-1.0.txt
json2capella-0.3.1.dist-info/METADATA
json2capella-0.3.1.dist-info/WHEEL
json2capella-0.3.1.dist-info/top_level.txt
json2capella-0.3.1.dist-info/RECORD
